<!DOCTYPE suite SYSTEM "https://testng.org/testng-1.0.dtd" >

<suite name="Class calistirma">
    <test name="Urun Sayfasindan Sepete Ekle">
        <classes>
            <class name="tests.Case2_UrunSayfasindanSepeteEkle.C01_HbUrunArama"></class>
            <class name="tests.Case2_UrunSayfasindanSepeteEkle.C02_FiyatAraligiTanimla"></class>
            <class name="tests.Case2_UrunSayfasindanSepeteEkle.C03_xUrununSayfasinaGit"></class>
            <class name="tests.Case2_UrunSayfasindanSepeteEkle.C04_SepeteEkleveDogrula"></class>
        </classes>
    </test>
</suite>